<?xml version="1.0" ?><deck><card code="LODT-23" side="0"/><card code="LODT-23" side="0"/><card code="LODT-23" side="0"/><card code="LODT-22" side="0"/><card code="LODT-19" side="0"/><card code="LODT-21" side="0"/><card code="TDGS-75" side="0"/><card code="TDGS-75" side="0"/><card code="LODT-18" side="0"/><card code="LODT-18" side="0"/><card code="LODT-25" side="0"/><card code="LODT-20" side="0"/><card code="LODT-20" side="0"/><card code="LODT-20" side="0"/><card code="LODT-82" side="0"/><card code="LODT-24" side="0"/><card code="LODT-24" side="0"/><card code="LODT-21" side="0"/><card code="LODT-26" side="0"/><card code="LODT-26" side="0"/><card code="LODT-26" side="0"/><card code="LODT-18" side="0"/><card code="TDGS-89" side="0"/><card code="TDGS-89" side="0"/><card code="TDGS-89" side="0"/><card code="LODT-52" side="0"/><card code="LODT-52" side="0"/><card code="LODT-52" side="0"/><card code="LODT-71" side="0"/><card code="GX04-2" side="0"/><card code="GX04-2" side="0"/><card code="GX04-2" side="0"/><card code="FET;SD5;SD6;YSDJ;YSDS;SD8;SD09;SDRL-40;30;28;29;30;26;26;29" side="0"/><card code="FET;SD5;SD6;YSDJ;YSDS;SD8;SD09;SDRL-40;30;28;29;30;26;26;29" side="0"/><card code="LODT-70" side="0"/><card code="LODT-70" side="0"/><card code="LODT-70" side="0"/><card code="LODT-53" side="0"/><card code="LODT-53" side="0"/><card code="LODT-89" side="0"/></deck>